my_mcp_gaodeweather_server/Tii.py
my_mcp_gaodeweather_server/__init__.py
my_mcp_gaodeweather_server/coo.py
my_mcp_gaodeweather_server/tools/foo.py
my_mcp_gaodeweather_server/utils/__init__.py
my_mcp_gaodeweather_server/utils/bar.py
my_mcp_gaodeweather_server-0.1.4.dist-info/METADATA
my_mcp_gaodeweather_server-0.1.4.dist-info/WHEEL
my_mcp_gaodeweather_server-0.1.4.dist-info/RECORD
